version_utils/__init__.py
version_utils/common.py
version_utils/errors.py
version_utils/rpm.py
version_utils/version.py
version_utils-0.3.2.dist-info/LICENSE
version_utils-0.3.2.dist-info/METADATA
version_utils-0.3.2.dist-info/WHEEL
version_utils-0.3.2.dist-info/top_level.txt
version_utils-0.3.2.dist-info/RECORD
