Metadata-Version: 2.1
Name: version-utils
Version: 0.3.2
Summary: Library for parsing system package strings and comparing package versions
Home-page: http://www.github.com/ihiji/version_utils
Author: Matthew Planchard
Author-email: mplanchard@ihiji.com
License: License :: OSI Approved :: GNU General Public License v3 (GPLv3)
Keywords: ihiji version compare parse rpm yum versions comparison utility utilities control distribution
Platform: UNKNOWN
Classifier: Development Status :: 3 - Alpha
Classifier: Environment :: Console
Classifier: Environment :: Plugins
Classifier: Intended Audience :: Developers
Classifier: License :: OSI Approved :: GNU General Public License v3 (GPLv3)
Classifier: Natural Language :: English
Classifier: Operating System :: OS Independent
Classifier: Programming Language :: Python :: 2.6
Classifier: Programming Language :: Python :: 2.7
Classifier: Programming Language :: Python :: 3
Classifier: Programming Language :: Python :: 3.4
Classifier: Programming Language :: Python :: 3.5
Classifier: Topic :: Software Development :: Libraries :: Python Modules
Classifier: Topic :: Software Development :: Version Control
Classifier: Topic :: System :: Software Distribution
Classifier: Topic :: Utilities
License-File: LICENSE
